poetry_deps_formatter/__init__.py
poetry_deps_formatter/formatter.py
poetry_deps_formatter-0.1.2.dist-info/METADATA
poetry_deps_formatter-0.1.2.dist-info/WHEEL
poetry_deps_formatter-0.1.2.dist-info/entry_points.txt
poetry_deps_formatter-0.1.2.dist-info/RECORD
