Metadata-Version: 2.1
Name: poetry-deps-formatter
Version: 0.1.2
Summary: Beautify dependencies in pyproject.yaml based on poetry.lock
Home-page: https://github.com/true-brains/poetry-deps-formatter
Author: Jack Klimov
Author-email: jaklimoff@gmail.com
Requires-Python: >=3.7,<4.0
Classifier: Programming Language :: Python :: 3
Classifier: Programming Language :: Python :: 3.7
Classifier: Programming Language :: Python :: 3.8
Classifier: Programming Language :: Python :: 3.9
Classifier: Programming Language :: Python :: 3.10
Classifier: Programming Language :: Python :: 3.11
Classifier: Programming Language :: Python :: 3.12
Classifier: Programming Language :: Python :: 3.13
Requires-Dist: toml (>=0.9.0)
Project-URL: Repository, https://github.com/true-brains/poetry-deps-formatter
